{
  "as_of": "2026-06-29 17:30:57 HKT",
  "trading_day": "2026-06-29",
  "stocks": [
    {
      "name": "绿的谐波",
      "code": "688017",
      "price": "361.62",
      "pct": "-2.1220",
      "sector": "robot",
      "sector_label": "🤖 人形机器人",
      "amplitude": 7.302549999999999,
      "turnover": 7.446999999999999,
      "amount_yi": 48.9
    },
    {
      "name": "雅克科技",
      "code": "002409",
      "price": "207.46",
      "pct": "10.0000",
      "sector": "gas_epi",
      "sector_label": "💨 电子特气 + 外延片",
      "amplitude": 8.632025,
      "turnover": 13.081999999999999,
      "amount_yi": 84.36
    },
    {
      "name": "三安光电",
      "code": "600703",
      "price": "21.06",
      "pct": "-3.0833",
      "sector": "mat",
      "sector_label": "🧪 半导体材料",
      "amplitude": 12.977451,
      "turnover": 10.577,
      "amount_yi": 112.59
    },
    {
      "name": "云南锗业",
      "code": "002428",
      "price": "124.0",
      "pct": "2.9216",
      "sector": "mat",
      "sector_label": "🧪 半导体材料",
      "amplitude": 10.715471,
      "turnover": 14.779,
      "amount_yi": 114.49
    },
    {
      "name": "立昂微",
      "code": "605358",
      "price": "78.89",
      "pct": "4.6703",
      "sector": "mat",
      "sector_label": "🧪 半导体材料",
      "amplitude": 13.121932,
      "turnover": 17.066,
      "amount_yi": 99.75
    },
    {
      "name": "北方华创",
      "code": "002371",
      "price": "860.19",
      "pct": "5.7563",
      "sector": "equip",
      "sector_label": "⚙️ 半导体设备",
      "amplitude": 8.603710000000001,
      "turnover": 2.073,
      "amount_yi": 125.4
    },
    {
      "name": "沪硅产业",
      "code": "688126",
      "price": "39.0",
      "pct": "11.8761",
      "sector": "mat",
      "sector_label": "🧪 半导体材料",
      "amplitude": 12.59323,
      "turnover": 9.857000000000001,
      "amount_yi": 105.58
    },
    {
      "name": "天孚通信",
      "code": "300394",
      "price": "295.15",
      "pct": "-7.1855",
      "sector": "cpo",
      "sector_label": "🔦 CPO / 光模块",
      "amplitude": 7.902515999999999,
      "turnover": 4.851,
      "amount_yi": 158.64
    },
    {
      "name": "拓荆科技",
      "code": "688072",
      "price": "832.0",
      "pct": "0.0000",
      "sector": "equip",
      "sector_label": "⚙️ 半导体设备",
      "amplitude": null,
      "turnover": 0.0,
      "amount_yi": null
    },
    {
      "name": "长电科技",
      "code": "600584",
      "price": "103.25",
      "pct": "2.3392",
      "sector": "packaging",
      "sector_label": "🔧 ASIC 封测",
      "amplitude": 13.281792000000001,
      "turnover": 18.227,
      "amount_yi": 324.4
    },
    {
      "name": "通富微电",
      "code": "002156",
      "price": "72.58",
      "pct": "1.3687",
      "sector": "packaging",
      "sector_label": "🔧 ASIC 封测",
      "amplitude": 11.089385,
      "turnover": 11.197,
      "amount_yi": 121.0
    },
    {
      "name": "昊华科技",
      "code": "600378",
      "price": "68.53",
      "pct": "10.0000",
      "sector": "gas_epi",
      "sector_label": "💨 电子特气 + 外延片",
      "amplitude": 15.922953000000001,
      "turnover": 8.474,
      "amount_yi": 58.58
    },
    {
      "name": "沃格光电",
      "code": "603773",
      "price": "163.35",
      "pct": "-8.2303",
      "sector": "tgv",
      "sector_label": "🧊 TGV / 玻璃基板",
      "amplitude": 13.421348,
      "turnover": 13.128,
      "amount_yi": 50.25
    },
    {
      "name": "中际旭创",
      "code": "300308",
      "price": "1220.0",
      "pct": "-2.7028",
      "sector": "cpo",
      "sector_label": "🔦 CPO / 光模块",
      "amplitude": 7.554092,
      "turnover": 3.179,
      "amount_yi": 426.32
    },
    {
      "name": "中船特气",
      "code": "688146",
      "price": "370.0",
      "pct": "-4.0456",
      "sector": "gas_epi",
      "sector_label": "💨 电子特气 + 外延片",
      "amplitude": 20.95695,
      "turnover": 14.904,
      "amount_yi": 76.94
    },
    {
      "name": "新易盛",
      "code": "300502",
      "price": "556.96",
      "pct": "-1.5972",
      "sector": "cpo",
      "sector_label": "🔦 CPO / 光模块",
      "amplitude": 9.14841,
      "turnover": 4.131,
      "amount_yi": 283.71
    },
    {
      "name": "金宏气体",
      "code": "688106",
      "price": "39.17",
      "pct": "13.5362",
      "sector": "gas_epi",
      "sector_label": "💨 电子特气 + 外延片",
      "amplitude": 11.188405999999999,
      "turnover": 12.995000000000001,
      "amount_yi": 26.59
    },
    {
      "name": "光库科技",
      "code": "300620",
      "price": "365.2",
      "pct": "0.7643",
      "sector": "cpo",
      "sector_label": "🔦 CPO / 光模块",
      "amplitude": 10.644814,
      "turnover": 5.838,
      "amount_yi": 53.56
    }
  ],
  "etf_top": [
    {
      "code": "589120.SH",
      "name": "汇添富上证科创板创新药etf",
      "price": "0.823",
      "pct": 11.669
    },
    {
      "code": "589720.SH",
      "name": "国泰上证科创板创新药etf",
      "price": "0.892",
      "pct": 11.5
    },
    {
      "code": "588710.SH",
      "name": "华泰柏瑞上证科创板半导体材料设备主题etf",
      "price": "4.102",
      "pct": 10.566
    },
    {
      "code": "588170.SH",
      "name": "华夏上证科创板半导体材料设备主题etf",
      "price": "3.961",
      "pct": 9.661999999999999
    },
    {
      "code": "589020.SH",
      "name": "鹏华科创板半导体材料设备主题etf",
      "price": "3.196",
      "pct": 9.64
    }
  ],
  "etf_bottom": [
    {
      "code": "512650.SH",
      "name": "添富中证长三角etf",
      "price": "1.476",
      "pct": -6.7
    },
    {
      "code": "159507.SZ",
      "name": "广发国证通信etf",
      "price": "1.070",
      "pct": -2.904
    },
    {
      "code": "159695.SZ",
      "name": "嘉实国证通信etf",
      "price": "3.510",
      "pct": -2.716
    },
    {
      "code": "563280.SH",
      "name": "富国msci中国a50互联互通增强策略etf",
      "price": "1.440",
      "pct": -2.439
    },
    {
      "code": "159583.SZ",
      "name": "富国中证通信设备主题etf",
      "price": "1.988",
      "pct": -2.406
    }
  ],
  "macro": {
    "cpi_yoy": {
      "value": 0.0,
      "date": "20251231",
      "unit": "%",
      "name": "CPI同比增长率"
    },
    "pmi": {
      "value": 50.0,
      "date": "20260531",
      "unit": "%",
      "name": "PMI"
    }
  }
}
